{
	"archive" : {},
	"artifacts" : 
	[
		{
			"path" : "libsoa.a"
		}
	],
	"backtrace" : 1,
	"backtraceGraph" : 
	{
		"commands" : 
		[
			"add_library",
			"add_compile_options"
		],
		"files" : 
		[
			"CMakeLists.txt"
		],
		"nodes" : 
		[
			{
				"file" : 0
			},
			{
				"command" : 0,
				"file" : 0,
				"line" : 12,
				"parent" : 0
			},
			{
				"command" : 1,
				"file" : 0,
				"line" : 7,
				"parent" : 0
			}
		]
	},
	"compileGroups" : 
	[
		{
			"compileCommandFragments" : 
			[
				{
					"fragment" : "-march=native -fdiagnostics-color=always"
				},
				{
					"backtrace" : 2,
					"fragment" : "-Wall"
				},
				{
					"backtrace" : 2,
					"fragment" : "-Wextra"
				},
				{
					"backtrace" : 2,
					"fragment" : "-Werror"
				},
				{
					"backtrace" : 2,
					"fragment" : "-pedantic"
				},
				{
					"backtrace" : 2,
					"fragment" : "-pedantic-errors"
				},
				{
					"fragment" : "-std=gnu++2a"
				}
			],
			"language" : "CXX",
			"languageStandard" : 
			{
				"backtraces" : 
				[
					1
				],
				"standard" : "20"
			},
			"sourceIndexes" : 
			[
				0
			]
		}
	],
	"id" : "soa::@6890427a1f51a3e7e1df",
	"name" : "soa",
	"nameOnDisk" : "libsoa.a",
	"paths" : 
	{
		"build" : ".",
		"source" : "."
	},
	"sourceGroups" : 
	[
		{
			"name" : "Source Files",
			"sourceIndexes" : 
			[
				0
			]
		}
	],
	"sources" : 
	[
		{
			"backtrace" : 1,
			"compileGroupIndex" : 0,
			"path" : "soa.cpp",
			"sourceGroupIndex" : 0
		}
	],
	"type" : "STATIC_LIBRARY"
}
